CHANGELOG.md
MANIFEST.in
README.md
_upload.txt
requirements.txt
setup.py
_deprecated/app/__init__.py
_deprecated/app/particles.py
_manifesto/Manifesto.md
_testenv/GUI/GUIapp.py
_testenv/pyscript/data.py
vandal/__init__.py
vandal/__main__.py
vandal.egg-info/PKG-INFO
vandal.egg-info/SOURCES.txt
vandal.egg-info/dependency_links.txt
vandal.egg-info/requires.txt
vandal.egg-info/top_level.txt
vandal/apps/__init__.py
vandal/apps/montecarlo_gui.py
vandal/hub/__init__.py
vandal/hub/example.py
vandal/hub/toolkit.py
vandal/misc/__init__.py
vandal/misc/_meta.py
vandal/objects/__init__.py
vandal/objects/dijkstra.py
vandal/objects/eoq.py
vandal/objects/montecarlo.py